volumentations/__init__.py
volumentations/augmentations/__init__.py
volumentations/augmentations/functional.py
volumentations/augmentations/transforms.py
volumentations/core/__init__.py
volumentations/core/composition.py
volumentations/core/serialization.py
volumentations/core/six.py
volumentations/core/transforms_interface.py
volumentations/core/utils.py
volumentations-0.1.9.dist-info/licenses/LICENSE
volumentations-0.1.9.dist-info/METADATA
volumentations-0.1.9.dist-info/WHEEL
volumentations-0.1.9.dist-info/top_level.txt
volumentations-0.1.9.dist-info/RECORD
