Metadata-Version: 2.4
Name: volumentations
Version: 0.1.9
Summary: Point augmentations library as hard-fork of albu-team/albumentations
Author-email: kumuji <alexey@nekrasov.dev>
License: MIT
Project-URL: homepage, https://github.com/kumuji/volumentations
Project-URL: repository, https://github.com/kumuji/volumentations
Project-URL: documentation, https://volumentations.readthedocs.io/en/latest/
Classifier: Development Status :: 3 - Alpha
Classifier: License :: OSI Approved :: MIT License
Classifier: Intended Audience :: Developers
Classifier: Intended Audience :: Science/Research
Classifier: Operating System :: OS Independent
Classifier: Programming Language :: Python
Classifier: Programming Language :: Python :: 3
Classifier: Programming Language :: Python :: 3.8
Classifier: Programming Language :: Python :: 3.9
Classifier: Programming Language :: Python :: 3.10
Classifier: Programming Language :: Python :: 3.11
Classifier: Programming Language :: Python :: 3.12
Classifier: Programming Language :: Python :: 3.13
Classifier: Topic :: Software Development :: Libraries
Classifier: Topic :: Software Development :: Libraries :: Python Modules
Classifier: Topic :: Scientific/Engineering :: Artificial Intelligence
Requires-Python: >=3.8.1
License-File: LICENSE
Requires-Dist: numpy>=1.22.0
Requires-Dist: pyyaml
Provides-Extra: dev
Requires-Dist: uv>=0.5.4; extra == "dev"
Requires-Dist: pytest>=8.3.5; extra == "dev"
Requires-Dist: flake8>=7.1.2; extra == "dev"
Requires-Dist: flake8-docstrings>=1.7.0; extra == "dev"
Requires-Dist: flake8-isort>=6.1.1; extra == "dev"
Requires-Dist: flake8-bandit>=4.1.1; extra == "dev"
Requires-Dist: flake8-black>=0.3.6; extra == "dev"
Requires-Dist: flake8-bugbear>=24.12.12; extra == "dev"
Requires-Dist: isort>=5.13.2; extra == "dev"
Requires-Dist: mypy>=1.14.1; extra == "dev"
Requires-Dist: pre-commit>=3.5.0; extra == "dev"
Requires-Dist: nox==2025.5.1; extra == "dev"
Requires-Dist: coverage[toml]>=7.6.1; extra == "dev"
Requires-Dist: pytest-cov>=5.0.0; extra == "dev"
Requires-Dist: pytest-mock>=3.14.0; extra == "dev"
Requires-Dist: xdoctest>=1.1.5; extra == "dev"
Requires-Dist: sphinx<7.0.0,>=6.2.1; extra == "dev"
Requires-Dist: sphinx-autodoc-typehints>=1.17.0; extra == "dev"
Requires-Dist: sphinx-rtd-theme<3.0.0,>=2.0.0; extra == "dev"
Requires-Dist: black>=24.8.0; extra == "dev"
Dynamic: license-file
